openpixels/__init__.py
openpixels/client.py
openpixels_python-0.0.1.dist-info/METADATA
openpixels_python-0.0.1.dist-info/WHEEL
openpixels_python-0.0.1.dist-info/entry_points.txt
openpixels_python-0.0.1.dist-info/licenses/LICENSE
openpixels_python-0.0.1.dist-info/RECORD
