Metadata-Version: 2.4
Name: openpixels-python
Version: 0.0.1
Summary: OpenPixels Python SDK
Author-Email: Robert <robert@openpixels.ai>
License-Expression: MIT
License-File: LICENSE
Classifier: Programming Language :: Python :: 3
Classifier: Operating System :: OS Independent
Project-URL: Homepage, https://openpixels.ai
Project-URL: Issues, https://github.com/openpixels-ai/openpixels-python/issues
Requires-Python: >=3.8
